stefan_on_software_renderer/__init__.py
stefan_on_software_renderer/renderer.py
stefan_on_software_renderer/test/__init__.py
stefan_on_software_renderer/test/example.html
stefan_on_software_renderer/test/example.md
stefan_on_software_renderer/test/test_renderer.py
test/__init__.py
test/example.html
test/example.md
test/test_renderer.py
stefan_on_software_renderer-0.1.0.dist-info/METADATA
stefan_on_software_renderer-0.1.0.dist-info/WHEEL
stefan_on_software_renderer-0.1.0.dist-info/top_level.txt
stefan_on_software_renderer-0.1.0.dist-info/RECORD
