Metadata-Version: 2.1
Name: stefan-on-software-renderer
Version: 0.1.0
Summary: A simple program that can render Markdown that includes custom XML tags.
Home-page: https://github.com/Stefan4472/Stefans-Blog
Author: Stefan Kussmaul
Author-email: stefan@stefanonsoftware.com
License: MIT
Keywords: markdown
Classifier: License :: OSI Approved :: MIT License
Classifier: Programming Language :: Python :: 3
Requires-Dist: markdown2 (==2.4.2)
Requires-Dist: pygments (==2.10.0)
Requires-Dist: beautifulsoup4 (==4.10.0)
